stock_indicators/__init__.py
stock_indicators/logging_config.py
stock_indicators/_cslib/__init__.py
stock_indicators/_cslib/runtimeconfig.json
stock_indicators/_cslib/lib/Skender.Stock.Indicators.dll
stock_indicators/_cstypes/__init__.py
stock_indicators/_cstypes/datetime.py
stock_indicators/_cstypes/decimal.py
stock_indicators/_cstypes/list.py
stock_indicators/indicators/__init__.py
stock_indicators/indicators/adl.py
stock_indicators/indicators/adx.py
stock_indicators/indicators/alligator.py
stock_indicators/indicators/alma.py
stock_indicators/indicators/aroon.py
stock_indicators/indicators/atr.py
stock_indicators/indicators/atr_stop.py
stock_indicators/indicators/awesome.py
stock_indicators/indicators/basic_quotes.py
stock_indicators/indicators/beta.py
stock_indicators/indicators/bollinger_bands.py
stock_indicators/indicators/bop.py
stock_indicators/indicators/cci.py
stock_indicators/indicators/chaikin_oscillator.py
stock_indicators/indicators/chandelier.py
stock_indicators/indicators/chop.py
stock_indicators/indicators/cmf.py
stock_indicators/indicators/cmo.py
stock_indicators/indicators/connors_rsi.py
stock_indicators/indicators/correlation.py
stock_indicators/indicators/dema.py
stock_indicators/indicators/doji.py
stock_indicators/indicators/donchian.py
stock_indicators/indicators/dpo.py
stock_indicators/indicators/dynamic.py
stock_indicators/indicators/elder_ray.py
stock_indicators/indicators/ema.py
stock_indicators/indicators/epma.py
stock_indicators/indicators/fcb.py
stock_indicators/indicators/fisher_transform.py
stock_indicators/indicators/force_index.py
stock_indicators/indicators/fractal.py
stock_indicators/indicators/gator.py
stock_indicators/indicators/heikin_ashi.py
stock_indicators/indicators/hma.py
stock_indicators/indicators/ht_trendline.py
stock_indicators/indicators/hurst.py
stock_indicators/indicators/ichimoku.py
stock_indicators/indicators/kama.py
stock_indicators/indicators/keltner.py
stock_indicators/indicators/kvo.py
stock_indicators-1.3.3.dist-info/LICENSE
stock_indicators-1.3.3.dist-info/METADATA
stock_indicators-1.3.3.dist-info/WHEEL
stock_indicators-1.3.3.dist-info/top_level.txt
stock_indicators-1.3.3.dist-info/RECORD
