Metadata-Version: 2.2
Name: stock-indicators
Version: 1.3.3
Summary: Stock Indicators for Python.  Send in historical price quotes and get back desired technical indicators such as Stochastic RSI, Average True Range, Parabolic SAR, etc.  Nothing more.
Author: Dave Skender
Maintainer: Dong-Geon Lee
License: Apache 2.0
Project-URL: Homepage, https://python.stockindicators.dev
Project-URL: Bug Tracker, https://github.com/facioquo/stock-indicators-python/issues
Project-URL: Documentation, https://python.stockindicators.dev
Project-URL: Source Code, https://github.com/facioquo/stock-indicators-python/tree/main
Project-URL: Release Notes, https://github.com/facioquo/stock-indicators-python/releases
Keywords: Stock Indicators,Technical Indicators,Market,Technical Analysis,Algorithmic,Trading,Trade,Momentum,Finance,Algorithm,Algo,AlgoTrading,Financial,Strategy,Chart,Charting,Oscillator,Overlay,Equity,Bitcoin,Crypto,Cryptocurrency,Forex,Quantitative,Historical,Quotes,Accumulation,Distribution,ADL,Aroon,True Range,ATR,Bollinger Bands,Commodity,CCI,Chandelier Exit,Chaikin Money Flow,CMF,MFI,Kaufman Adaptive,Moving Average,Convergence,Divergence,MACD,SMA,EMA,DEMA,TEMA,TRIX,Smoothed,Elder-ray,Bul
Classifier: Intended Audience :: Developers
Classifier: Topic :: Office/Business :: Financial
Classifier: Topic :: Office/Business :: Financial :: Investment
Classifier: Programming Language :: Python
Classifier: Programming Language :: Python :: 3
Classifier: Programming Language :: Python :: 3.9
Classifier: Programming Language :: Python :: 3.10
Classifier: Programming Language :: Python :: 3.11
Classifier: Programming Language :: Python :: 3.12
Classifier: License :: OSI Approved :: Apache Software License
Classifier: Operating System :: OS Independent
Classifier: Operating System :: POSIX
Classifier: Operating System :: Unix
Classifier: Operating System :: MacOS
Classifier: Typing :: Typed
Requires-Python: >=3.8
License-File: LICENSE
Requires-Dist: pythonnet>=3.0.0
Requires-Dist: typing_extensions>=4.4.0
